packagebb/__init__.py
packagebb-0.0.3.dist-info/License.txt
packagebb-0.0.3.dist-info/METADATA
packagebb-0.0.3.dist-info/WHEEL
packagebb-0.0.3.dist-info/top_level.txt
packagebb-0.0.3.dist-info/RECORD
