Metadata-Version: 2.1
Name: packagebb
Version: 0.0.3
Summary: A very basic adding library
Home-page: UNKNOWN
Author: Joshua Lowe
Author-email: balajibetadur@gmail.com
License: MIT
Keywords: adding
Platform: UNKNOWN
